whoopapi/__init__.py
whoopapi/constants.py
whoopapi/logging.py
whoopapi/responses.py
whoopapi/utilities.py
whoopapi/wrappers.py
whoopapi/parsers/__init__.py
whoopapi/parsers/http_body.py
whoopapi/parsers/http_headers.py
whoopapi/protocol_handlers/__init__.py
whoopapi/protocol_handlers/http.py
whoopapi/protocol_handlers/websocket.py
whoopapi-0.0.2.dist-info/licenses/LICENSE
whoopapi-0.0.2.dist-info/METADATA
whoopapi-0.0.2.dist-info/WHEEL
whoopapi-0.0.2.dist-info/top_level.txt
whoopapi-0.0.2.dist-info/RECORD
