Metadata-Version: 2.4
Name: whoopapi
Version: 0.0.2
Summary: A lightweight web API framework.
Author-email: Derrick Wafula <derrickwafula@gmail.com>
License-Expression: MIT
Project-URL: Homepage, https://github.com/DerrohXy/WhoopAPI
Project-URL: Issues, https://github.com/DerrohXy/WhoopAPI/issues
Classifier: Programming Language :: Python :: 3
Classifier: Operating System :: OS Independent
Requires-Python: >=3.9
License-File: LICENSE
Requires-Dist: brotli>=1.1.0
Dynamic: license-file
